Floating Point IEEE 754 Multiplication/practice/Multiplication-2.v
module Multiplication(input [32-1:0] a,
                        input [32-1:0] b,
                        output exception, 
                        output overflow,
                        output underflow,
                        output [32-1:0] res);

wire sign;
wire round;
wire normalised;
wire zero;
wire [9-1:0] exponent;
// 9th bit for checking overflow(1_0000_0000) and underflow(1_1111_1111)
wire [9-1:0] sum_exponent;
// exponent before Bias(127)
wire [23-1:0] op_a;
wire [23-1:0] op_b;
wire [48-1:0] product;
wire [48-1:0] product_normalised;
wire [23-1:0] product_mantissa;

assign sign = a[31]^b[31];  // XOR of 32nd bit
assign exception = (&a[30:23]) | (&b[30:23]);
// Exception sets to 1 when exponent of any a or b is 255 which is for alert.
// If exponent is 0, hidden bit is 0, not 1. -> Definition of FP32

// verilator lint_off WIDTH
assign op_a= (|a[30:23]) ? {1'b1, a[22:0]} : {1'b0, a[22:0]};
// op_a gets additional 1 for exponent of nonzero
assign op_b= (|b[30:23]) ? {1'b1, b[22:0]} : {1'b0, b[22:0]};
// op_b gets additional 1 for exponent of nonzero
// verilator lint_on WIDTH

assign product = op_a * op_b;
// Product of two significant figures
assign round = |product_normalised[22:0];
// Last 22 bits are ORed for rounding off(BurRim or Cutoff) purpose
// 23 bit becomes into 1 bit
assign normalised = product[47] ? 1'b1 : 1'b0;
// See if it is normal number or not
assign product_normalised = normalised ? product : product << 1;
// Normalized value based on 48th bit
// If it is not normalised, we shift by 2 to the 1
// verilator lint_off WIDTH
assign product_mantissa = product_normalised[46:24] + 
                            (product_normalised[23] & round);
// verilator lint_on WIDTH
// Mantissa
assign zero = exception ? 1'b0 : (product_mantissa == 23'd0) ? 1'b1 : 1'b0;
// Nested conditions for finding 0 expression of FP32
assign sum_exponent = a[30:23] + b[30:23];
// multiplication of 2^exponent -> sum of exponents
// verilator lint_off WIDTH
assign exponent = sum_exponent - 8'd127 + normalised;
// verilator lint_on WIDTH
// exponent bias setting -> refer to definition of FP32
assign overflow = ((exponent[8] & !exponent[7]) & !zero);
// If overall exponet is greater than 255 then Overflow
// Condition for overflow
assign underflow = ((exponent[8] & exponent[7]) & !zero) ? 1'b1 : 1'b0;
// If sum of exponents is less than 255 then Underflow
// Condition for underflow
assign res = exception ? 32'd0 : 
                                zero ? {sign, 31'd0} : 
                                overflow ? {sign, 8'hFF, 23'd0} :
                                underflow ? {sign, 31'd0} : 
                                {sign, exponent[8-1:0], product_mantissa};

endmodule

module multiplication_tb;

reg [32-1:0] a;
reg [32-1:0] b;
wire exception;
wire overflow;
wire underflow;
wire [32-1:0] res;

reg clk= 1'b1;

Multiplication dut(a,
                    b,
                    exception,
                    overflow,
                    underflow,
                    res);

always clk = #5 ~clk;
// Period: 5+5

// Code for watching waveform
initial
begin
    $dumpfile("Multiplication.vcd");  // any file name possible
    $dumpvars(0, multiplication_tb);  // instance name required
end

task iteration(input [32-1:0] op_a,
                input [32-1:0] op_b,
                input Expected_Exception,
                input Expected_Overflow,
                input Expected_Underflow,
                input [32-1:0] Expected_result,
                input integer linenum);

begin
    @(negedge clk)
    begin
        a = op_a;
        b = op_b;
    end

    @(posedge clk)
    begin
        if((Expected_result == res) && 
            (Expected_Exception == exception) && 
            (Expected_Overflow == overflow) && 
            (Expected_Underflow == underflow))
            $display("Success : %d", linenum);

        else
        begin
            $display("Failed : ",
                        "Expected_result = %h, Result = %h, \n ",
                        Expected_result,
                        res,
                        "Expected_Exception = %d, Exception = %d, \n ",
                        Expected_Exception,
                        exception,
                        "Expected_Overflow = %d, Overflow = %d, \n ",
                        Expected_Overflow,
                        overflow,
                        "Expected_Underflow = %d, Underflow = %d - %d \n ", 
                        Expected_Underflow,
                        underflow,
                        linenum);
        end
    end
end
endtask



initial
begin
    iteration(32'h0200_0000, 
                32'h0200_0000,
                1'b0,
                1'b0,
                1'b0,
                32'h0000_0000,
                `__LINE__);

    iteration(32'h4234_851F,
                32'h427C_851F,
                1'b0,
                1'b0,
                1'b0,
                32'h4532_10E9,
                `__LINE__);
    // 45.13 * 63.13 = 2849.0569

    iteration(32'h4049_999A,
                32'hC166_3D71,
                1'b0,
                1'b0,
                1'b0,
                32'hC235_5062,
                `__LINE__);
    // 3.15 * -14.39 = -45.3285

    iteration(32'hC152_6666,
                32'hC240_A3D7,
                1'b0,
                1'b0,
                1'b0,
                32'h441E_5375,
                `__LINE__);
    // -13.15 * -48.16 = 633.304

    iteration(32'h4580_0000,
                32'h4580_0000,
                1'b0,
                1'b0,
                1'b0,
                32'h4B80_0000,
                `__LINE__);
    // 4096 * 4096 = 16777216

    iteration(32'h3ACA_62C1,
                32'h3ACA_62C1,
                1'b0,
                1'b0,
                1'b0,
                32'h361F_FFE7,
                `__LINE__);
    // 0.00154408081 * 0.00154408081 = 0.00000238418

    iteration(32'h0000_0000,
                32'h0000_0000,
                1'b0,
                1'b0,
                1'b0,
                32'h0000_0000,
                `__LINE__);
    // 0 * 0 = 0

    iteration(32'hC152_6666,
                32'h0000_0000,
                1'b0,
                1'b0,
                1'b0,
                32'h441E_5375,
                `__LINE__);
    // -13.15 * 0 = 0

    iteration(32'h7F80_0000,
                32'h7F80_0000,
                1'b1,
                1'b1,
                1'b0,
                32'h0000_0000,
                `__LINE__);

    // $stop;

    $finish;

end

endmodule

Floating Point IEEE 754 Multiplication/practice/Multiplication.vcd
$date
	Thu Oct 17 16:05:56 2024
$end
$version
	Icarus Verilog
$end
$timescale
	1s
$end
$scope module multiplication_tb $end
$var wire 1 ! underflow $end
$var wire 32 " res [31:0] $end
$var wire 1 # overflow $end
$var wire 1 $ exception $end
$var reg 32 % a [31:0] $end
$var reg 32 & b [31:0] $end
$var reg 1 ' clk $end
$scope module dut $end
$var wire 32 ( a [31:0] $end
$var wire 32 ) b [31:0] $end
$var wire 1 $ exception $end
$var wire 1 # overflow $end
$var wire 1 * sign $end
$var wire 1 + zero $end
$var wire 1 ! underflow $end
$var wire 9 , sum_exponent [8:0] $end
$var wire 1 - round $end
$var wire 32 . res [31:0] $end
$var wire 48 / product_normalised [47:0] $end
$var wire 23 0 product_mantissa [22:0] $end
$var wire 48 1 product [47:0] $end
$var wire 24 2 op_b [23:0] $end
$var wire 24 3 op_a [23:0] $end
$var wire 1 4 normalised $end
$var wire 9 5 exponent [8:0] $end
$upscope $end
$scope task iteration $end
$var reg 1 6 Expected_Exception $end
$var reg 1 7 Expected_Overflow $end
$var reg 1 8 Expected_Underflow $end
$var reg 32 9 Expected_result [31:0] $end
$var reg 32 : op_a [31:0] $end
$var reg 32 ; op_b [31:0] $end
$var integer 32 < linenum [31:0] $end
$upscope $end
$upscope $end
$enddefinitions $end
#0
$dumpvars
b10111001 <
b10000000000000000000000000 ;
b10000000000000000000000000 :
b0 9
08
07
06
bx 5
x4
bx 3
bx 2
bx 1
bx 0
bx /
bx .
x-
bx ,
x+
x*
bx )
bx (
1'
bx &
bx %
x$
x#
bx "
x!
$end
#5
0!
b0 0
0#
0-
0+
04
b0 "
b0 .
b100000000000000000000000000000000000000000000000 /
b0 5
b10000000000000000000000000000000000000000000000 1
b100000000000000000000000 2
0*
0$
b100000000000000000000000 3
b1000 ,
b10000000000000000000000000 &
b10000000000000000000000000 )
b10000000000000000000000000 %
b10000000000000000000000000 (
0'
#10
b11000001 <
b1000101001100100001000011101001 9
b1000010011111001000010100011111 ;
b1000010001101001000010100011111 :
1'
#15
b1000101001100100001000011101010 "
b1000101001100100001000011101010 .
1-
b1100100001000011101010 0
14
b101100100001000011101001100010010011100111000001 /
b10001010 5
b111111001000010100011111 2
b101100100001000011101001100010010011100111000001 1
b101101001000010100011111 3
b100001000 ,
b1000010011111001000010100011111 &
b1000010011111001000010100011111 )
b1000010001101001000010100011111 %
b1000010001101001000010100011111 (
0'
#20
b11001010 <
b11000010001101010101000001100010 9
b11000001011001100011110101110001 ;
b1000000010010011001100110011010 :
1'
#25
b11000010001101010101000001100011 "
b11000010001101010101000001100011 .
b1101010101000001100011 0
b101101010101000001100010111100100111111011111010 /
1*
b111001100011110101110001 2
b101101010101000001100010111100100111111011111010 1
b110010011001100110011010 3
b10000100 5
b100000010 ,
b11000001011001100011110101110001 &
b11000001011001100011110101110001 )
b1000000010010011001100110011010 %
b1000000010010011001100110011010 (
0'
#30
b11010011 <
b1000100000111100101001101110101 9
b11000010010000001010001111010111 ;
b11000001010100100110011001100110 :
1'
#35
b1000100000111100101001101110100 "
b1000100000111100101001101110100 .
b111100101001101110100 0
b100111100101001101110100011001101111000110101010 /
b110000001010001111010111 2
0*
b100111100101001101110100011001101111000110101010 1
b110100100110011001100110 3
b10001000 5
b100000110 ,
b11000010010000001010001111010111 &
b11000010010000001010001111010111 )
b11000001010100100110011001100110 %
b11000001010100100110011001100110 (
0'
#40
b11011100 <
b1001011100000000000000000000000 9
b1000101100000000000000000000000 ;
b1000101100000000000000000000000 :
1'
#45
b1001011100000000000000000000000 "
b1001011100000000000000000000000 .
04
0-
b0 0
b100000000000000000000000000000000000000000000000 /
b100000000000000000000000 2
b10000000000000000000000000000000000000000000000 1
b100000000000000000000000 3
b10010111 5
b100010110 ,
b1000101100000000000000000000000 &
b1000101100000000000000000000000 )
b1000101100000000000000000000000 %
b1000101100000000000000000000000 (
0'
#50
b11100101 <
b110110000111111111111111100111 9
b111010110010100110001011000001 ;
b111010110010100110001011000001 :
1'
#55
b110110000111111111111111111111 "
b110110000111111111111111111111 .
1-
b111111111111111111111 0
14
b100111111111111111111110101011000101010110000001 /
b110010100110001011000001 2
b100111111111111111111110101011000101010110000001 1
b110010100110001011000001 3
b1101100 5
b11101010 ,
b111010110010100110001011000001 &
b111010110010100110001011000001 )
b111010110010100110001011000001 %
b111010110010100110001011000001 (
0'
#60
b11101110 <
b0 9
b0 ;
b0 :
1'
#65
1+
b0 "
b0 .
0!
04
0-
b0 0
b0 /
b0 2
b0 1
b0 3
b0 5
b0 ,
b0 &
b0 )
b0 %
b0 (
0'
#70
b11110111 <
b10000000000000000000000000000000 9
b11000001010100100110011001100110 :
1'
#75
b10000000000000000000000000000000 "
b10000000000000000000000000000000 .
b11 5
1*
b110100100110011001100110 3
b10000010 ,
b11000001010100100110011001100110 %
b11000001010100100110011001100110 (
0'
#80
b100000000 <
b0 9
17
16
b1111111100000000000000000000000 ;
b1111111100000000000000000000000 :
1'
#85
b100000000000000000000000000000000000000000000000 /
1#
0+
b0 "
b0 .
b10000000000000000000000000000000000000000000000 1
b100000000000000000000000 2
0*
1$
b100000000000000000000000 3
b101111111 5
b111111110 ,
b1111111100000000000000000000000 &
b1111111100000000000000000000000 )
b1111111100000000000000000000000 %
b1111111100000000000000000000000 (
0'
